README.md
setup.cfg
setup.py
vrconcept_arhdron/Client.py
vrconcept_arhdron/Data.py
vrconcept_arhdron/__init__.py
vrconcept_arhdron.egg-info/PKG-INFO
vrconcept_arhdron.egg-info/SOURCES.txt
vrconcept_arhdron.egg-info/dependency_links.txt
vrconcept_arhdron.egg-info/not-zip-safe
vrconcept_arhdron.egg-info/top_level.txt