Metadata-Version: 2.1
Name: vrconcept_arhdron
Version: 1.0
Summary: VR Concept Arhipelag dron
Author-email: govoruxin.a1999@gmail.com
